{
    "categoriaGeneral": 
        {
            "categoria": "Categorías por área",
            "subcategorias": ["Programación","Electrónica","Inteligencia Artificial","Redes","Mecánica","Medicina","Química","Biotecnología","Estadística","Economía"]
        },

    "categoriasDeBotones": [
        {
            "categoria": "Programación",
            "subcategorias":["Django","Flask","Pandas","Machine learning","Deep learning"],
            "icono": "fas fa-laptop-code",
            "idClass": "programacion"
        },

        {
            "categoria": "Electrónica",
            "subcategorias": ["Electrónica de potencia","Análisis de circuitos CC","Análisis de circuitos CA","Electrónica digital","Semiconductores","Electrónica Industrial","Control"],
            "icono":"fas fa-car-battery",
            "idClass": "electronica"
        },

        {
            "categoria": "Int Artificial",
            "subcategorias": ["Redes neuronales","Machine learning","Deep learning","Máquinas vectoriales","Análisis de PCA","Aprendizaje supervizado","Aprendizaje no supervizado","Clusttering"],
            "icono": "fas fa-brain",
            "idClass": "intArtificial"
        },

        {
            "categoria": "Redes",
            "subcategorias": ["Internet de las cosas","Redes neuronales","Ciberseguridad","Redes informáticas y seguridad","Redes infromáticas y hacking","Marketing","Marketing en redes sociales","Redes de computadoras"],
            "icono":"fas fa-network-wired",
            "idClass": "redes"
        },

        {
            "categoria": "Mecánica",
            "subcategorias": ["Mecánica de materiales","Mecánica automotriz","Estática","Dinámica","Resistencia de materiales","Mecánica de fluidos","Mecanismos","Aire acondicionado","Estructuras de concreto","Termodinámica"],
            "icono": "fas fa-cogs",
            "idClass": "mecanica"
        },
            
        {
            "categoria": "Medicina",
            "subcategorias": ["Diabetes","Cardiología","Neurología","Farmacología","Epidemiología","Anestesiología","Oncología","Pediatría","Bacteriología","Ginecología","Microbiología","Neurología"],
            "icono": "fas fa-stethoscope",
            "idClass": "medicina"
        }, 

        {
            "categoria": "Química",
            "subcategorias": ["Química orgánica","Fotoquímica","Química inorgánica","Polímeros","Estequiometría","Catálisis","Química nuclear","Química forense","Fenómenos de transporte","Balance de masa y energía"],
            "icono": "fas fa-atom",
            "idClass": "quimica"
        },
        
        {
            "categoria":"Biotecnología",
            "subcategorias": ["Ingeniería genética","Clonación","Enzimas de restricción","Productos biotecnológicos","Bioinformática","Bioníca","Biorremediación","Células madres","Órganos artificiales"],
            "icono": "fas fa-leaf",
            "idClass": "biotecnologia"
        }, 

        {
            "categoria":"Estadística",
            "subcategorias": ["Estadística descriptica","Estadística inferencial","Análisis de datos","Estadística analítica","Medidas de biodiversidad","Estadística aplicada","Asociaciones de estadística","Leyes estadísticas"],
            "icono": "fas fa-chart-pie",
            "idClass": "estadistica"
        }, 

        {
            "categoria":"Economía",
            "subcategorias": ["Ciencia económica","Contabilidad","Derecho económico","Econometría","Economía y medio ambiente","Monedas circulantes","Negocios","Inversiones en la bolsa","Unidades de cuenta", "Macroeconomía","Microeconomía"],
            "icono": "fas fa-chart-line",
            "idClass": "economia"
        }
    ],

    "categoriasCheckbox":[
        {
            "titulo": "Libros por idioma",
            "categoria": "idioma",
            "valor": ["ingles","español","frances","italiano"],
            "subcategorias":[" Inglés"," Español"," Francés"," Italiano"]
        },

        {
            "titulo": "Libros por formato",
            "categoria": "formato",
            "valor": ["ebook","blanda","dura"],
            "subcategorias":[" Ebooks"," Pasta blanda"," Pasta dura"]
        },

        {
            "titulo": "Promociones",
            "categoria": "promociones",
            "valor": ["promociones"],
            "subcategorias":[" Promociones"]
        }
    ],

    "opinionesClientes":{
        "titulo": "Opiniones de los clientes",
        "subcategorias": [
            {
                "opinion": 4,
                "idClass": "first"
            },

            {
                "opinion": 3,
                "idClass": ""
            },

            {
                "opinion": 2,
                "idClass": ""
            },
            
            {
                "opinion": 1,
                "idClass": ""
            }
        ]
    },

    "precios": {
        "titulo": "Precio",
        "subcategorias": ["Hasta $50","$50 a $100","$100 a $200","$200 a $300","$300 a $500","$500 a más"]
    }

}